{
  "Common Program Specific": {
    "Income_and_Sources": {
      "Information_Date": "[date field]",
      "Income_from_Any_Source": {
        "Responses": {
          "0": "No",
          "1": "Yes",
          "8": "Client doesn't know",
          "9": "Client prefers not to answer",
          "99": "Data not collected"
        }
      },
      "Earned_Income": {
        "Responses": {
          "0": "No",
          "1": "Yes"
        }
      },
      "Unemployment_Insurance": {
        "Responses": {
          "0": "No",
          "1": "Yes"
        }
      },
      "Supplemental_Security_Income": {
        "Responses": {
          "0": "No",
          "1": "Yes"
        }
      },
      "Social_Security_Disability_Insurance": {
        "Responses": {
          "0": "No",
          "1": "Yes"
        }
      },
      "VA_Service_Connected_Disability": {
        "Responses": {
          "0": "No",
          "1": "Yes"
        }
      },
      "VA_Non_Service_Connected_Disability": {
        "Responses": {
          "0": "No",
          "1": "Yes"
        }
      },
      "Private_Disability_Insurance": {
        "Responses": {
          "0": "No",
          "1": "Yes"
        }
      },
      "Workers_Compensation": {
        "Responses": {
          "0": "No",
          "1": "Yes"
        }
      },
      "TANF": {
        "Responses": {
          "0": "No",
          "1": "Yes"
        }
      },
      "General_Assistance": {
        "Responses": {
          "0": "No",
          "1": "Yes"
        }
      },
      "Retirement_Income_Social_Security": {
        "Responses": {
          "0": "No",
          "1": "Yes"
        }
      },
      "Pension_Former_Job": {
        "Responses": {
          "0": "No",
          "1": "Yes"
        }
      },
      "Child_Support": {
        "Responses": {
          "0": "No",
          "1": "Yes"
        }
      },
      "Alimony": {
        "Responses": {
          "0": "No",
          "1": "Yes"
        }
      },
      "Other_Source": {
        "Responses": {
          "0": "No",
          "1": "Yes"
        }
      },
      "Total_Monthly_Income": "[currency/decimal]",
      "Dependents": [
        {
          "Name": "Monthly Amount",
          "Description": "Dependent to Earned Income & Response 1",
          "Parent_Field": "Earned_Income",
          "Trigger_Value": "1",
          "Field_Type": "[currency/decimal]"
        },
        {
          "Name": "Monthly Amount",
          "Description": "Dependent to Unemployment Insurance & Response 1",
          "Parent_Field": "Unemployment_Insurance",
          "Trigger_Value": "1",
          "Field_Type": "[currency/decimal]"
        },
        {
          "Name": "Monthly Amount",
          "Description": "Dependent to SSI & Response 1",
          "Parent_Field": "Supplemental_Security_Income",
          "Trigger_Value": "1",
          "Field_Type": "[currency/decimal]"
        },
        {
          "Name": "Monthly Amount",
          "Description": "Dependent to SSDI & Response 1",
          "Parent_Field": "Social_Security_Disability_Insurance",
          "Trigger_Value": "1",
          "Field_Type": "[currency/decimal]"
        },
        {
          "Name": "Monthly Amount",
          "Description": "Dependent to VA Service-Connected & Response 1",
          "Parent_Field": "VA_Service_Connected_Disability",
          "Trigger_Value": "1",
          "Field_Type": "[currency/decimal]"
        },
        {
          "Name": "Monthly Amount",
          "Description": "Dependent to VA Non-Service-Connected & Response 1",
          "Parent_Field": "VA_Non_Service_Connected_Disability",
          "Trigger_Value": "1",
          "Field_Type": "[currency/decimal]"
        },
        {
          "Name": "Monthly Amount",
          "Description": "Dependent to Private Disability & Response 1",
          "Parent_Field": "Private_Disability_Insurance",
          "Trigger_Value": "1",
          "Field_Type": "[currency/decimal]"
        },
        {
          "Name": "Monthly Amount",
          "Description": "Dependent to Worker's Compensation & Response 1",
          "Parent_Field": "Workers_Compensation",
          "Trigger_Value": "1",
          "Field_Type": "[currency/decimal]"
        },
        {
          "Name": "Monthly Amount",
          "Description": "Dependent to TANF & Response 1",
          "Parent_Field": "TANF",
          "Trigger_Value": "1",
          "Field_Type": "[currency/decimal]"
        },
        {
          "Name": "Monthly Amount",
          "Description": "Dependent to GA & Response 1",
          "Parent_Field": "General_Assistance",
          "Trigger_Value": "1",
          "Field_Type": "[currency/decimal]"
        },
        {
          "Name": "Monthly Amount",
          "Description": "Dependent to Social Security Retirement & Response 1",
          "Parent_Field": "Retirement_Income_Social_Security",
          "Trigger_Value": "1",
          "Field_Type": "[currency/decimal]"
        },
        {
          "Name": "Monthly Amount",
          "Description": "Dependent to Pension & Response 1",
          "Parent_Field": "Pension_Former_Job",
          "Trigger_Value": "1",
          "Field_Type": "[currency/decimal]"
        },
        {
          "Name": "Monthly Amount",
          "Description": "Dependent to Child Support & Response 1",
          "Parent_Field": "Child_Support",
          "Trigger_Value": "1",
          "Field_Type": "[currency/decimal]"
        },
        {
          "Name": "Monthly Amount",
          "Description": "Dependent to Alimony & Response 1",
          "Parent_Field": "Alimony",
          "Trigger_Value": "1",
          "Field_Type": "[currency/decimal]"
        },
        {
          "Name": "Monthly Amount",
          "Description": "Dependent to Other Source & Response 1",
          "Parent_Field": "Other_Source",
          "Trigger_Value": "1",
          "Field_Type": "[currency/decimal]"
        },
        {
          "Name": "Specify Source",
          "Description": "Dependent to Other Source & Response 1",
          "Parent_Field": "Other_Source",
          "Trigger_Value": "1",
          "Field_Type": "[text field]"
        }
      ]
    },
    "Non_Cash_Benefits": {
      "Information_Date": "[date field]",
      "Benefits_from_Any_Source": {
        "Responses": {
          "0": "No",
          "1": "Yes",
          "8": "Client doesn't know",
          "9": "Client prefers not to answer",
          "99": "Data not collected"
        }
      },
      "SNAP": {
        "Responses": {
          "0": "No",
          "1": "Yes"
        }
      },
      "WIC": {
        "Responses": {
          "0": "No",
          "1": "Yes"
        }
      },
      "TANF_Child_Care": {
        "Responses": {
          "0": "No",
          "1": "Yes"
        }
      },
      "TANF_Transportation": {
        "Responses": {
          "0": "No",
          "1": "Yes"
        }
      },
      "Other_TANF_Services": {
        "Responses": {
          "0": "No",
          "1": "Yes"
        }
      },
      "Other_Source": {
        "Responses": {
          "0": "No",
          "1": "Yes"
        }
      },
      "Dependents": [
        {
          "Name": "Specify_Source",
          "Description": "If Yes for Other Source",
          "Parent_Field": "Other_Source",
          "Trigger_Value": "1",
          "Field_Type": "[text field]"
        }
      ]
    },
    "Health_Insurance": {
      "Information_Date": "[date field]",
      "Covered_by_Health_Insurance": {
        "Responses": {
          "0": "No",
          "1": "Yes",
          "8": "Client doesn't know",
          "9": "Client prefers not to answer",
          "99": "Data not collected"
        }
      },
      "Medicaid": {
        "Responses": {
          "0": "No",
          "1": "Yes"
        }
      },
      "Medicare": {
        "Responses": {
          "0": "No",
          "1": "Yes"
        }
      },
      "State_Childrens_Health_Insurance": {
        "Responses": {
          "0": "No",
          "1": "Yes"
        }
      },
      "VA_Health_Administration": {
        "Responses": {
          "0": "No",
          "1": "Yes"
        }
      },
      "Employer_Provided": {
        "Responses": {
          "0": "No",
          "1": "Yes"
        }
      },
      "COBRA": {
        "Responses": {
          "0": "No",
          "1": "Yes"
        }
      },
      "Private_Pay": {
        "Responses": {
          "0": "No",
          "1": "Yes"
        }
      },
      "State_Health_Insurance": {
        "Responses": {
          "0": "No",
          "1": "Yes"
        }
      },
      "Indian_Health_Services": {
        "Responses": {
          "0": "No",
          "1": "Yes"
        }
      },
      "Other_Insurance": {
        "Responses": {
          "0": "No",
          "1": "Yes"
        }
      },
      "Dependents": [
        {
          "Name": "HOPWA_Reason",
          "Description": "HOPWA FIELD ONLY - If No",
          "Parent_Field": "Medicaid",
          "Trigger_Value": "0",
          "Responses": {
            "1": "Applied; decision pending",
            "2": "Applied; client not eligible",
            "3": "Client did not apply",
            "4": "Insurance type N/A for this client",
            "8": "Client doesn't know",
            "9": "Client prefers not to answer",
            "99": "Data not collected"
          }
        },
        {
          "Name": "Specify_Source",
          "Description": "If Yes for Other Insurance",
          "Parent_Field": "Other_Insurance",
          "Trigger_Value": "1",
          "Field_Type": "[text field]"
        }
      ]
    },
    "Physical_Disability": {
      "Information_Date": "[date field]",
      "Has_Physical_Disability": {
        "Responses": {
          "0": "No",
          "1": "Yes",
          "8": "Client doesn't know",
          "9": "Client prefers not to answer",
          "99": "Data not collected"
        }
      },
      "Dependents": [
        {
          "Name": "Long_Term_Impact",
          "Description": "If Yes for Physical Disability",
          "Parent_Field": "Has_Physical_Disability",
          "Trigger_Value": "1",
          "Responses": {
            "0": "No",
            "1": "Yes",
            "8": "Client doesn't know",
            "9": "Client prefers not to answer",
            "99": "Data not collected"
          }
        }
      ]
    },
    "Developmental_Disability": {
      "Information_Date": "[date field]",
      "Has_Developmental_Disability": {
        "Responses": {
          "0": "No",
          "1": "Yes",
          "8": "Client doesn't know",
          "9": "Client prefers not to answer",
          "99": "Data not collected"
        }
      }
    },
    "Chronic_Health_Condition": {
      "Information_Date": "[date field]",
      "Has_Chronic_Health_Condition": {
        "Responses": {
          "0": "No",
          "1": "Yes",
          "8": "Client doesn't know",
          "9": "Client prefers not to answer",
          "99": "Data not collected"
        }
      },
      "Dependents": [
        {
          "Name": "Long_Term_Impact",
          "Description": "If Yes for Chronic Health Condition",
          "Parent_Field": "Has_Chronic_Health_Condition",
          "Trigger_Value": "1",
          "Responses": {
            "0": "No",
            "1": "Yes",
            "8": "Client doesn't know",
            "9": "Client prefers not to answer",
            "99": "Data not collected"
          }
        }
      ]
    },
    "HIV_AIDS": {
      "Information_Date": "[date field]",
      "Has_HIV_AIDS": {
        "Responses": {
          "0": "No",
          "1": "Yes",
          "8": "Client doesn't know",
          "9": "Client prefers not to answer",
          "99": "Data not collected"
        }
      }
    },
    "Mental_Health_Disorder": {
      "Information_Date": "[date field]",
      "Has_Mental_Health_Disorder": {
        "Responses": {
          "0": "No",
          "1": "Yes",
          "8": "Client doesn't know",
          "9": "Client prefers not to answer",
          "99": "Data not collected"
        }
      },
      "Dependents": [
        {
          "Name": "Long_Term_Impact",
          "Description": "If Yes for Mental Health Disorder",
          "Parent_Field": "Has_Mental_Health_Disorder",
          "Trigger_Value": "1",
          "Responses": {
            "0": "No",
            "1": "Yes",
            "8": "Client doesn't know",
            "9": "Client prefers not to answer",
            "99": "Data not collected"
          }
        }
      ]
    },
    "Substance_Use_Disorder": {
      "Information_Date": "[date field]",
      "Has_Substance_Use_Disorder": {
        "Responses": {
          "0": "No",
          "1": "Alcohol use disorder",
          "2": "Drug use disorder",
          "3": "Both alcohol and drug use disorders",
          "8": "Client doesn't know",
          "9": "Client prefers not to answer",
          "99": "Data not collected"
        }
      },
      "Dependents": [
        {
          "Name": "Long_Term_Impact",
          "Description": "If Substance Use Disorder present",
          "Parent_Field": "Has_Substance_Use_Disorder",
          "Trigger_Value": ["1", "2", "3"],
          "Responses": {
            "0": "No",
            "1": "Yes",
            "8": "Client doesn't know",
            "9": "Client prefers not to answer",
            "99": "Data not collected"
          }
        }
      ]
    },
    "Domestic_Violence": {
      "Information_Date": "[date field]",
      "Survivor_of_Domestic_Violence": {
        "Responses": {
          "0": "No",
          "1": "Yes",
          "8": "Client doesn't know",
          "9": "Client prefers not to answer",
          "99": "Data not collected"
        }
      },
      "Dependents": [
        {
          "Name": "When_Experience_Occurred",
          "Description": "If Yes for Survivor of Domestic Violence",
          "Parent_Field": "Survivor_of_Domestic_Violence",
          "Trigger_Value": "1",
          "Responses": {
            "1": "Within the past three months",
            "2": "Three to six months ago (excluding six months exactly)",
            "3": "Six months to one year ago (excluding one year exactly)",
            "4": "One year ago, or more",
            "8": "Client doesn't know",
            "9": "Client prefers not to answer",
            "99": "Data not collected"
          }
        },
        {
          "Name": "Currently_Fleeing",
          "Description": "If Yes for Survivor of Domestic Violence",
          "Parent_Field": "Survivor_of_Domestic_Violence",
          "Trigger_Value": "1",
          "Responses": {
            "0": "No",
            "1": "Yes",
            "8": "Client doesn't know",
            "9": "Client prefers not to answer",
            "99": "Data not collected"
          }
        }
      ]
    },
    "Current_Living_Situation": {
      "Information_Date": "[date field]",
      "Living_Situation": {
        "Description": "Current Living Situation [See Appendix A]",
        "Responses": {
          "116": "Place not meant for habitation (e.g., a vehicle, an abandoned building, bus/train/subway station/airport or anywhere outside)",
          "101": "Emergency shelter, including hotel or motel paid for with emergency shelter voucher, Host Home shelter",
          "118": "Safe Haven",
          "215": "Foster care home or foster care group home",
          "206": "Hospital or other residential non-psychiatric medical facility",
          "207": "Jail, prison, or juvenile detention facility",
          "225": "Long-term care facility or nursing home",
          "204": "Psychiatric hospital or other psychiatric facility",
          "205": "Substance abuse treatment facility or detox center",
          "302": "Transitional housing for homeless persons (including homeless youth)",
          "329": "Residential project or halfway house with no homeless criteria",
          "314": "Hotel or motel paid for without emergency shelter voucher",
          "332": "Host Home (non-crisis)",
          "336": "Staying or living in a friend’s room, apartment, or house",
          "335": "Staying or living in a family member’s room, apartment, or house",
          "410": "Rental by client, no ongoing housing subsidy",
          "435": "Rental by client, with ongoing housing subsidy",
          "421": "Owned by client, with ongoing housing subsidy",
          "411": "Owned by client, no ongoing housing subsidy",
          "17": "Other",
          "37": "Worker unable to determine",
          "8": "Client doesn’t know",
          "9": "Client prefers not to answer",
          "99": "Data not collected"
        }
      },
      "Living_Situation_Verified_By": "[list of Continuum projects]",
      "Location_Details": "[text field]",
      "Dependents": [
        {
          "Name": "Rental_Subsidy_Type",
          "Description": "Dependent to Response 435",
          "Parent_Field": "Living_Situation",
          "Trigger_Value": "435",
          "Rental Subsidy Type": {
            "Responses": {
              "428": "GPD TIP housing subsidy",
              "419": "VASH housing subsidy",
              "431": "RRH or equivalent subsidy",
              "433": "HCV voucher (tenant or project based) (not dedicated)",
              "434": "Public housing unit",
              "420": "Rental by client, with other ongoing housing subsidy",
              "436": "Housing Stability Voucher",
              "437": "Family Unification Program Voucher (FUP)",
              "438": "Foster Youth to Independence Initiative (FYI)",
              "439": "Permanent Supportive Housing",
              "440": "Other permanent housing dedicated for formerly homeless persons"
            }
          }
        },
        {
          "Name": "Will_Leave_Within_14_Days",
          "Description": "For all non-homeless situations (17, 37, and 200-499)",
          "Parent_Field": "Living_Situation",
          "Trigger_Value": ["17", "37", "200-499"],
          "Responses": {
            "0": "No",
            "1": "Yes",
            "8": "Client doesn't know",
            "9": "Client prefers not to answer",
            "99": "Data not collected"
          },
          "Sub_Dependents": [
            {
              "Name": "Subsequent_Residence",
              "Description": "If Yes to leaving within 14 days",
              "Parent_Field": "Will_Leave_Within_14_Days",
              "Trigger_Value": "1",
              "Responses": {
                "0": "No",
                "1": "Yes",
                "8": "Client doesn't know",
                "9": "Client prefers not to answer",
                "99": "Data not collected"
              }
            },
            {
              "Name": "Resources_For_Housing",
              "Description": "If Yes to leaving within 14 days",
              "Parent_Field": "Will_Leave_Within_14_Days",
              "Trigger_Value": "1",
              "Responses": {
                "0": "No",
                "1": "Yes",
                "8": "Client doesn't know",
                "9": "Client prefers not to answer",
                "99": "Data not collected"
              }
            },
            {
              "Name": "Prior_Lease",
              "Description": "If Yes to leaving within 14 days",
              "Parent_Field": "Will_Leave_Within_14_Days",
              "Trigger_Value": "1",
              "Responses": {
                "0": "No",
                "1": "Yes",
                "8": "Client doesn't know",
                "9": "Client prefers not to answer",
                "99": "Data not collected"
              }
            },
            {
              "Name": "Multiple_Moves",
              "Description": "If Yes to leaving within 14 days",
              "Parent_Field": "Will_Leave_Within_14_Days",
              "Trigger_Value": "1",
              "Responses": {
                "0": "No",
                "1": "Yes",
                "8": "Client doesn't know",
                "9": "Client prefers not to answer",
                "99": "Data not collected"
              }
            }
          ]
        }
      ]
    },
    "Date_of_Engagement": {
      "Date_of_Engagement": "[date field]"
    },
    "Bed_Night_Date": {
      "Bed_Night_Date": "[date field]"
    },
    "Coordinated_Entry_Assessment": {
      "Assessment_Date": "[date field]",
      "Assessment_Location": {
        "Response": "[drop down]"
      },
      "Assessment_Type": {
        "Responses": {
          "1": "Phone",
          "2": "Virtual",
          "3": "In person"
        }
      },
      "Assessment_Level": {
        "Responses": {
          "1": "Crisis Needs Assessment",
          "2": "Housing Needs Assessment"
        }
      },
      "Assessment_Questions": {
        "Description": "Local determination - as defined by the community",
        "Values": "[array of locally defined questions]",
        "Dependents": [
          {
            "Name": "Assessment_Answers",
            "Description": "Answers for locally defined questions",
            "Parent_Field": "Assessment_Questions",
            "Response": "[array of answers corresponding to questions]"
          }
        ]
      },
      "Assessment_Result_Type": {
        "Description": "Local determination - as defined by the community",
        "Values": "[array of locally defined result types]",
        "Dependents": [
          {
            "Name": "Assessment_Results",
            "Description": "Results for each result type",
            "Parent_Field": "Assessment_Result_Type",
            "Response": "[array of results corresponding to result types]"
          }
        ]
      },
      "Prioritization_Status": {
        "Responses": {
          "1": "Placed on prioritization list",
          "2": "Not placed on prioritization list"
        }
      }
    },
    "Coordinated_Entry_Event": {
      "Event_Date": "[date field]",
      "Event": {
        "Headers": {
          "Access_Events": {
            "Responses": {
              "1": "Referral to Prevention Assistance project",
              "2": "Problem Solving/Diversion/Rapid Resolution intervention or service",
              "3": "Referral to scheduled Coordinated Entry Crisis Needs Assessment",
              "4": "Referral to scheduled Coordinated Entry Housing Needs Assessment"
            }
          },
          "Referral_Events": {
            "Responses": {
              "5": "Referral to post-placement/follow-up case management",
              "6": "Referral to Street Outreach project or services",
              "7": "Referral to Housing Navigation project or services",
              "8": "Referral to Non-continuum services: Ineligible for continuum services",
              "9": "Referral to Non-continuum services: No availability in continuum services",
              "10": "Referral to Emergency Shelter bed opening",
              "11": "Referral to Transitional Housing bed/unit opening",
              "12": "Referral to Joint TH-RRH project/unit/resource opening",
              "13": "Referral to RRH project resource opening",
              "14": "Referral to PSH project resource opening",
              "15": "Referral to Other PH project/unit/resource opening",
              "16": "Referral to emergency assistance/flex fund/furniture assistance",
              "18": "Referral to a Housing Stability Voucher"
            }
          }
        },
        "Dependents": [
          {
            "Name": "Problem_Solving_Result",
            "Description": "If Problem Solving/Diversion/Rapid Resolution intervention",
            "Parent_Field": "Event",
            "Trigger_Value": "2",
            "Responses": {
              "0": "No",
              "1": "Yes"
            }
          },
          {
            "Name": "Aftercare_Enrollment",
            "Description": "If Referral to post-placement/follow-up case management",
            "Parent_Field": "Event",
            "Trigger_Value": "5",
            "Responses": {
              "0": "No",
              "1": "Yes"
            }
          },
          {
            "Name": "Location_of_Housing",
            "Description": "If Housing Referral",
            "Parent_Field": "Event",
            "Trigger_Value": ["10", "11", "12", "13", "14", "15"],
            "Response": "[Project name and/or Project ID]"
          },
          {
            "Name": "Referral_Result",
            "Description": "If Housing or Voucher Referral",
            "Parent_Field": "Event",
            "Trigger_Value": ["10", "11", "12", "13", "14", "15", "18"],
            "Responses": {
              "1": "Successful referral: client accepted",
              "2": "Unsuccessful referral: client rejected",
              "3": "Unsuccessful referral: provider rejected"
            },
            "Sub_Dependents": [
              {
                "Name": "Result_Date",
                "Description": "Date of referral result",
                "Parent_Field": "Referral_Result",
                "Field_Type": "[date field]"
              }
            ]
          }
        ]
      }
    }
  }
}
